LICENSE
MANIFEST.in
README.rst
VERSION
setup.cfg
setup.py
signalfx_instrumentation_tornado.egg-info/PKG-INFO
signalfx_instrumentation_tornado.egg-info/SOURCES.txt
signalfx_instrumentation_tornado.egg-info/dependency_links.txt
signalfx_instrumentation_tornado.egg-info/requires.txt
signalfx_instrumentation_tornado.egg-info/top_level.txt
tornado_opentracing/__init__.py
tornado_opentracing/_constants.py
tornado_opentracing/_tracing.py
tornado_opentracing/_tracing_async.py
tornado_opentracing/application.py
tornado_opentracing/context_managers.py
tornado_opentracing/handlers.py
tornado_opentracing/httpclient.py
tornado_opentracing/initialization.py
tornado_opentracing/scope_managers.py
tornado_opentracing/tracing.py