Metadata-Version: 2.1
Name: signalfx-instrumentation-tornado
Version: 1.0.0
Summary: OpenTracing support for Tornado applications
Home-page: https://github.com/signalfx/python-tornado/
Author: SignalFx, Inc.
Author-email: signalfx-oss@splunk.com
License: Apache License 2.0
Download-URL: https://github.com/signalfx/python-tornado/tarball/1.0.0
Platform: any
Classifier: Environment :: Web Environment
Classifier: Intended Audience :: Developers
Classifier: License :: OSI Approved :: BSD License
Classifier: Operating System :: OS Independent
Classifier: Programming Language :: Python
Classifier: Topic :: Internet :: WWW/HTTP :: Dynamic Content
Classifier: Topic :: Software Development :: Libraries :: Python Modules
Provides-Extra: tests
